segmentation_models_pytorch/__init__.py
segmentation_models_pytorch/__version__.py
segmentation_models_pytorch/base/__init__.py
segmentation_models_pytorch/base/heads.py
segmentation_models_pytorch/base/initialization.py
segmentation_models_pytorch/base/model.py
segmentation_models_pytorch/base/modules.py
segmentation_models_pytorch/deeplabv3/__init__.py
segmentation_models_pytorch/deeplabv3/decoder.py
segmentation_models_pytorch/deeplabv3/model.py
segmentation_models_pytorch/encoders/__init__.py
segmentation_models_pytorch/encoders/_base.py
segmentation_models_pytorch/encoders/_preprocessing.py
segmentation_models_pytorch/encoders/_utils.py
segmentation_models_pytorch/encoders/densenet.py
segmentation_models_pytorch/encoders/dpn.py
segmentation_models_pytorch/encoders/efficientnet.py
segmentation_models_pytorch/encoders/inceptionresnetv2.py
segmentation_models_pytorch/encoders/inceptionv4.py
segmentation_models_pytorch/encoders/mobilenet.py
segmentation_models_pytorch/encoders/resnet.py
segmentation_models_pytorch/encoders/senet.py
segmentation_models_pytorch/encoders/timm_efficientnet.py
segmentation_models_pytorch/encoders/timm_regnet.py
segmentation_models_pytorch/encoders/timm_res2net.py
segmentation_models_pytorch/encoders/timm_resnest.py
segmentation_models_pytorch/encoders/timm_sknet.py
segmentation_models_pytorch/encoders/vgg.py
segmentation_models_pytorch/encoders/xception.py
segmentation_models_pytorch/fpn/__init__.py
segmentation_models_pytorch/fpn/decoder.py
segmentation_models_pytorch/fpn/model.py
segmentation_models_pytorch/linknet/__init__.py
segmentation_models_pytorch/linknet/decoder.py
segmentation_models_pytorch/linknet/model.py
segmentation_models_pytorch/pan/__init__.py
segmentation_models_pytorch/pan/decoder.py
segmentation_models_pytorch/pan/model.py
segmentation_models_pytorch/pspnet/__init__.py
segmentation_models_pytorch/pspnet/decoder.py
segmentation_models_pytorch/pspnet/model.py
segmentation_models_pytorch/unet/__init__.py
d3m_segmentation_models_pytorch-0.1.3.dist-info/LICENSE
d3m_segmentation_models_pytorch-0.1.3.dist-info/METADATA
d3m_segmentation_models_pytorch-0.1.3.dist-info/WHEEL
d3m_segmentation_models_pytorch-0.1.3.dist-info/top_level.txt
d3m_segmentation_models_pytorch-0.1.3.dist-info/RECORD
