Metadata-Version: 2.1
Name: d3m-segmentation-models-pytorch
Version: 0.1.3
Summary: Image segmentation models with pre-trained backbones. PyTorch.
Home-page: https://github.com/qubvel/segmentation_models.pytorch
Author: Pavel Yakubovskiy
Author-email: qubvel@gmail.com
License: MIT
Platform: UNKNOWN
Classifier: License :: OSI Approved :: MIT License
Classifier: Programming Language :: Python
Classifier: Programming Language :: Python :: 3
Classifier: Programming Language :: Python :: Implementation :: CPython
Classifier: Programming Language :: Python :: Implementation :: PyPy
Requires-Python: >=3.0.0
License-File: LICENSE
Requires-Dist: torchvision (>=0.3.0)
Requires-Dist: pretrainedmodels (==0.7.4)
Requires-Dist: efficientnet-pytorch (>=0.6.3)
Requires-Dist: timm (==0.3.2)
Provides-Extra: test
Requires-Dist: pytest ; extra == 'test'
